odoo/addons/website_sale_google_tag_manager/README.rst
odoo/addons/website_sale_google_tag_manager/__init__.py
odoo/addons/website_sale_google_tag_manager/__manifest__.py
odoo/addons/website_sale_google_tag_manager/i18n/website_sale_google_tag_manager.pot
odoo/addons/website_sale_google_tag_manager/models/__init__.py
odoo/addons/website_sale_google_tag_manager/models/res_config_settings.py
odoo/addons/website_sale_google_tag_manager/models/website.py
odoo/addons/website_sale_google_tag_manager/readme/CONFIGURE.rst
odoo/addons/website_sale_google_tag_manager/readme/CONTRIBUTORS.rst
odoo/addons/website_sale_google_tag_manager/readme/DESCRIPTION.rst
odoo/addons/website_sale_google_tag_manager/static/description/icon.png
odoo/addons/website_sale_google_tag_manager/static/description/index.html
odoo/addons/website_sale_google_tag_manager/static/description/website_google_tag_manager.jpg
odoo/addons/website_sale_google_tag_manager/views/res_config_settings_view.xml
odoo/addons/website_sale_google_tag_manager/views/website_templates.xml
odoo13_addon_website_sale_google_tag_manager-13.0.1.0.1.dev3.dist-info/METADATA
odoo13_addon_website_sale_google_tag_manager-13.0.1.0.1.dev3.dist-info/WHEEL
odoo13_addon_website_sale_google_tag_manager-13.0.1.0.1.dev3.dist-info/top_level.txt
odoo13_addon_website_sale_google_tag_manager-13.0.1.0.1.dev3.dist-info/RECORD
